setup.py
datalab/__init__.py
datalab/miscellaneous.py
datalab/libs/__init__.py
datalab/libs/cmreslogging/__init__.py
datalab/libs/cmreslogging/handlers.py
datalab/libs/cmreslogging/serializers.py
datalab/src/__init__.py
datalab/src/connections/__init__.py
datalab/src/connections/connections.py
datalab/src/currators/__init__.py
datalab/src/currators/delete_old_indexes.py
datalab/src/es_monitoring/__init__.py
datalab/src/es_monitoring/es_monitoring.py
datalab/src/importers/__init__.py
datalab/src/importers/collectors_importers.py
datalab/src/importers/csv_importers.py
datalab/src/importers/datalab_importers.py
datalab/src/importers/es_impoters.py
datalab/src/importers/kairos_importers.py
datalab/src/importers/online_reader.py
datalab/src/importers/samp_importers.py
datalab/src/loggers/__init__.py
datalab/src/loggers/datalab_loggers.py
datalab/src/queries/2pandas.py
datalab/src/queries/__init__.py
datalab/src/queries/esQueries.py
datalab/templates/__init__.py
datalab/templates/mapping/__init__.py
datalab/templates/mapping/opslog.py
datalab/templates/mapping/vltlog.py
datalab/tests/__init__.py
datalab/tests/collector_importers.py
datalab/tests/csv_importers.py
datalab/tests/datalab_importers.py
datalab/tests/elastic_importers.py
datalab/tests/kairos_importers.py
datalab/tests/samp_importers.py
jose_datalab.egg-info/PKG-INFO
jose_datalab.egg-info/SOURCES.txt
jose_datalab.egg-info/dependency_links.txt
jose_datalab.egg-info/top_level.txt