Metadata-Version: 1.1
Name: jose-datalab
Version: 0.1.1
Summary: Datalab project python-api
Home-page: https://github.com/josemanuel22/-fluffy-couscous.git
Author: Jose Manuel de Frutos Porras
Author-email: josem.frutos@estudiante.uam.es
License: UNKNOWN
Keywords: datalab project
Platform: UNKNOWN
Classifier: Development Status :: 3 - Alpha
Classifier: Intended Audience :: Developers
Classifier: Topic :: Software Development :: Build Tools
Classifier: Programming Language :: Python :: 3
Classifier: Programming Language :: Python :: 3.3
Classifier: Programming Language :: Python :: 3.4
Classifier: Programming Language :: Python :: 3.5
Classifier: Programming Language :: Python :: 3.6
